README.md
setup.py
miniot_7seg/AFSevenSegment.py
miniot_7seg/HT16K33.py
miniot_7seg/JSSevenSegment.py
miniot_7seg/SevenSegment.py
miniot_7seg/__init__.py
miniot_7seg/display.py
miniot_7seg.egg-info/PKG-INFO
miniot_7seg.egg-info/SOURCES.txt
miniot_7seg.egg-info/dependency_links.txt
miniot_7seg.egg-info/not-zip-safe
miniot_7seg.egg-info/top_level.txt
miniot_7seg/js/knockout-2.2.1.js
miniot_7seg/js/sevenSeg.js