Metadata-Version: 1.1
Name: miniot-7seg
Version: 0.82
Summary: A library to control Adafruit LED backpack displays, and to show LED image in Jupyter Notebook cell.
Home-page: https://github.com/shibats/miniot_7seg/
Author: Atsushi Shibata
Author-email: shibata@m-info.co.jp
License: MIT
Platform: UNKNOWN
Classifier: Development Status :: 4 - Beta
Classifier: Operating System :: POSIX :: Linux
Classifier: Operating System :: MacOS :: MacOS X
Classifier: Operating System :: Microsoft :: Windows
Classifier: License :: OSI Approved :: MIT License
Classifier: Intended Audience :: Developers
Classifier: Programming Language :: Python :: 3
Classifier: Topic :: Software Development
Classifier: Topic :: System :: Hardware
